sub_platforms/__init__.py
sub_platforms/sql_opt/__init__.py
sub_platforms/sql_opt/meta.py
sub_platforms/sql_opt/column_statastics/__init__.py
sub_platforms/sql_opt/column_statastics/statistics_info.py
sub_platforms/sql_opt/common/__init__.py
sub_platforms/sql_opt/common/db_variable.py
sub_platforms/sql_opt/common/exceptions.py
sub_platforms/sql_opt/common/sample_file_info.py
sub_platforms/sql_opt/common/sample_info.py
sub_platforms/sql_opt/databases/__init__.py
sub_platforms/sql_opt/databases/mysql/__init__.py
sub_platforms/sql_opt/databases/mysql/common_operation.py
sub_platforms/sql_opt/databases/mysql/explain_result.py
sub_platforms/sql_opt/databases/mysql/mysql_command.py
sub_platforms/sql_opt/env/__init__.py
sub_platforms/sql_opt/env/rds_env.py
sub_platforms/sql_opt/histogram/__init__.py
sub_platforms/sql_opt/histogram/histogram_utils.py
sub_platforms/sql_opt/histogram/ndv_estimator.py
sub_platforms/sql_opt/sql_opt_utils/__init__.py
sub_platforms/sql_opt/sql_opt_utils/sqlbrain_constants.py
sub_platforms/sql_opt/videx/__init__.py
sub_platforms/sql_opt/videx/videx_histogram.py
sub_platforms/sql_opt/videx/videx_logging.py
sub_platforms/sql_opt/videx/videx_metadata.py
sub_platforms/sql_opt/videx/videx_mysql_utils.py
sub_platforms/sql_opt/videx/videx_service.py
sub_platforms/sql_opt/videx/videx_strategy.py
sub_platforms/sql_opt/videx/videx_utils.py
sub_platforms/sql_opt/videx/common/__init__.py
sub_platforms/sql_opt/videx/common/estimate_stats_length.py
sub_platforms/sql_opt/videx/model/__init__.py
sub_platforms/sql_opt/videx/model/videx_model_example.py
sub_platforms/sql_opt/videx/model/videx_model_innodb.py
sub_platforms/sql_opt/videx/model/videx_strategy.py
sub_platforms/sql_opt/videx/scripts/__init__.py
sub_platforms/sql_opt/videx/scripts/start_videx_server.py
sub_platforms/sql_opt/videx/scripts/videx_build_env.py
sub_platforms/sql_opt/videx/scripts/analyze/__init__.py
sub_platforms/sql_opt/videx/scripts/analyze/analyze_delete_rows.py
videx-0.0.3.dist-info/LICENSES.md
videx-0.0.3.dist-info/METADATA
videx-0.0.3.dist-info/WHEEL
videx-0.0.3.dist-info/top_level.txt
videx-0.0.3.dist-info/RECORD
