Metadata-Version: 2.2
Name: videx
Version: 0.0.3
Summary: videx, the Disaggregated, Extensible Virtual Index Engine for What-If Analysis
Author-email: kangrong <kr11thss@gmail.com>
License: MIT and GPL-2.0
Project-URL: Homepage, https://github.com/bytedance/videx
Project-URL: Repository, https://github.com/bytedance/videx
Project-URL: Documentation, https://github.com/bytedance/videx/blob/main/README.md
Project-URL: Bug Tracker, https://github.com/bytedance/videx/issues
Keywords: index,database,what-if,mysql,virtual index
Classifier: Development Status :: 3 - Alpha
Classifier: Intended Audience :: Developers
Classifier: Topic :: Software Development :: Build Tools
Classifier: License :: OSI Approved :: MIT License
Classifier: License :: OSI Approved :: GNU General Public License v2 (GPLv2)
Classifier: Programming Language :: Python :: 3
Classifier: Programming Language :: Python :: 3.9
Classifier: Programming Language :: Python :: 3.10
Classifier: Programming Language :: Python :: 3 :: Only
Requires-Python: >=3.9
License-File: LICENSES.md
Requires-Dist: DBUtils==3.0.3
Requires-Dist: msgpack==1.0.5
Requires-Dist: numpy==1.24.4
Requires-Dist: pandas==2.0.3
Requires-Dist: pyarrow==12.0.1
Requires-Dist: PyMySQL==0.9.3
Requires-Dist: requests==2.29.0
Requires-Dist: SQLAlchemy==2.0.18
Requires-Dist: dataclasses-json==0.5.13
Requires-Dist: pyyaml==6.0.1
Requires-Dist: tqdm==4.65.2
Requires-Dist: matplotlib==3.7.2
Requires-Dist: Flask==2.3.3
Requires-Dist: gunicorn~=21.2.0
Requires-Dist: psutil==5.9.5
Requires-Dist: retrying==1.3.4
Requires-Dist: setuptools==75.6.0
Requires-Dist: Werkzeug==3.1.3
Requires-Dist: pyDes~=2.0.1
Requires-Dist: cachetools~=5.3.3
Requires-Dist: estndv==0.0.2
Requires-Dist: sqlglot==25.4.1
Requires-Dist: pydantic==2.10.4
